cursus/__init__.py
cursus/__version__.py
cursus/api/__init__.py
cursus/api/config_ui/__init__.py
cursus/api/config_ui/enhanced_widget.py
cursus/api/config_ui/run_server.py
cursus/api/config_ui/start_server.py
cursus/api/config_ui/core/__init__.py
cursus/api/config_ui/core/core.py
cursus/api/config_ui/core/data_sources_manager.py
cursus/api/config_ui/core/field_definitions.py
cursus/api/config_ui/core/import_utils.py
cursus/api/config_ui/core/utils.py
cursus/api/config_ui/web/__init__.py
cursus/api/config_ui/web/api.py
cursus/api/config_ui/widgets/__init__.py
cursus/api/config_ui/widgets/cradle_native_widget.py
cursus/api/config_ui/widgets/jupyter_widget.py
cursus/api/config_ui/widgets/native.py
cursus/api/config_ui/widgets/specialized_widgets.py
cursus/api/config_ui/widgets/widget.py
cursus/api/cradle_ui/__init__.py
cursus/api/cradle_ui/app.py
cursus/api/cradle_ui/example_notebook_usage.py
cursus/api/cradle_ui/jupyter_widget.py
cursus/api/cradle_ui/api/__init__.py
cursus/api/cradle_ui/api/routes.py
cursus/api/cradle_ui/schemas/__init__.py
cursus/api/cradle_ui/schemas/request_schemas.py
cursus/api/cradle_ui/schemas/response_schemas.py
cursus/api/cradle_ui/services/__init__.py
cursus/api/cradle_ui/services/config_builder.py
cursus/api/cradle_ui/services/validation_service.py
cursus/api/cradle_ui/utils/__init__.py
cursus/api/cradle_ui/utils/config_loader.py
cursus/api/dag/__init__.py
cursus/api/dag/base_dag.py
cursus/api/dag/pipeline_dag_resolver.py
cursus/api/factory/__init__.py
cursus/api/factory/config_class_mapper.py
cursus/api/factory/configuration_generator.py
cursus/api/factory/dag_config_factory.py
cursus/api/factory/field_extractor.py
cursus/cli/__init__.py
cursus/cli/__main__.py
cursus/cli/alignment_cli.py
cursus/cli/builder_test_cli.py
cursus/cli/catalog_cli.py
cursus/cli/pipeline_cli.py
cursus/cli/registry_cli.py
cursus/cli/script_testing_cli.py
cursus/cli/workspace_cli.py
cursus/core/__init__.py
cursus/core/assembler/__init__.py
cursus-1.4.7.dist-info/licenses/LICENSE
cursus-1.4.7.dist-info/METADATA
cursus-1.4.7.dist-info/WHEEL
cursus-1.4.7.dist-info/entry_points.txt
cursus-1.4.7.dist-info/top_level.txt
cursus-1.4.7.dist-info/RECORD
